dynamic_filenames/__init__.py
dynamic_filenames/_version.py
django_dynamic_filenames-1.4.1.dist-info/licenses/LICENSE
django_dynamic_filenames-1.4.1.dist-info/WHEEL
django_dynamic_filenames-1.4.1.dist-info/METADATA
django_dynamic_filenames-1.4.1.dist-info/RECORD
