Metadata-Version: 2.4
Name: django-dynamic-filenames
Version: 1.4.1
Summary: Write advanced filename patterns using the Format String Syntax.
Keywords: django,django-storages,file,filenames,django-pictures
Author-email: Johannes Maron <johannes@maron.family>
Requires-Python: >=3.10
Classifier: Development Status :: 5 - Production/Stable
Classifier: Programming Language :: Python
Classifier: Environment :: Web Environment
Classifier: Intended Audience :: Developers
Classifier: License :: OSI Approved :: MIT License
Classifier: Operating System :: OS Independent
Classifier: Programming Language :: Python
Classifier: Topic :: Software Development
Classifier: Programming Language :: JavaScript
Classifier: Programming Language :: Python :: 3
Classifier: Programming Language :: Python :: 3 :: Only
Classifier: Programming Language :: Python :: 3.10
Classifier: Programming Language :: Python :: 3.11
Classifier: Programming Language :: Python :: 3.12
Classifier: Programming Language :: Python :: 3.13
Classifier: Programming Language :: Python :: 3.14
Classifier: Framework :: Django
Classifier: Framework :: Django :: 4.2
Classifier: Framework :: Django :: 5.2
Classifier: Framework :: Django :: 6.0
License-File: LICENSE
Requires-Dist: django>=4.2.0
Project-URL: Changelog, https://github.com/codingjoe/django-dynamic-filenames/releases
Project-URL: Documentation, https://github.com/codingjoe/django-dynamic-filenames?tab=readme-ov-file
Project-URL: Funding, https://github.com/sponsors/codingjoe
Project-URL: Homepage, https://github.com/codingjoe/django-dynamic-filenames
Project-URL: Issues, https://github.com/codingjoe/django-dynamic-filenames/issues
Project-URL: Releasenotes, https://github.com/codingjoe/django-dynamic-filenames/releases/latest
Project-URL: Source, https://github.com/codingjoe/django-dynamic-filenames
